{
    "OMC":[
        {
            "id":1,
            "name":"AH_OMC2_15MIN.html",
            "img":"",
            "url":"www.baidu.com"
        },{
            "id":2,
            "name":"ZJ_OMC25_15MIN.html",
            "img":"",
            "url":"www.baidu.com"
        },{
            "id":3,
            "name":"ZJ_OMC11_15MIN.html",
            "img":"",
            "url":"www.baidu.com"
        },{
            "id":4,
            "name":"ZJ_OMC3_15MIN.html",
            "img":"",
            "url":"www.baidu.com"
        },{
            "id":5,
            "name":"JS_OMC16_15MIN.html",
            "img":"",
            "url":"www.baidu.com"
        },{
            "id":6,
            "name":"JS_OMC12_15MIN.html",
            "img":"",
            "url":"www.baidu.com"
        },{
            "id":7,
            "name":"ZJ_OMC10_15MIN.html",
            "img":"",
            "url":"www.baidu.com"
        },{
            "id":8,
            "name":"ZJ_OMC9_15MIN.html",
            "img":"",
            "url":"www.baidu.com"
        },{
            "id":9,
            "name":"ZJ_OMC6_15MIN.html",
            "img":"",
            "url":"www.baidu.com"
        },{
            "id":10,
            "name":"GD_OMC26_15MIN.html",
            "img":"",
            "url":"www.baidu.com"
        },{
            "id":11,
            "name":"GD_OMC18_15MIN.html",
            "img":"",
            "url":"www.baidu.com"
        },{
            "id":12,
            "name":"GD_OMC13_15MIN.html",
            "img":"",
            "url":"www.baidu.com"
        },{
            "id":13,
            "name":"GD_OMC5_15MIN.html",
            "img":"",
            "url":"www.baidu.com"
        }
    ]
}